LICENSE
README.md
pyproject.toml
src/aliyun_mcp_skill/__init__.py
src/aliyun_mcp_skill/weather_skill.py
src/aliyun_mcp_weather_skill_20260130.egg-info/PKG-INFO
src/aliyun_mcp_weather_skill_20260130.egg-info/SOURCES.txt
src/aliyun_mcp_weather_skill_20260130.egg-info/dependency_links.txt
src/aliyun_mcp_weather_skill_20260130.egg-info/top_level.txt