Metadata-Version: 2.4
Name: aliyun-mcp-weather-skill-20260130
Version: 0.1.0
Summary: Weather query skill for Aliyun Model Context Protocol (MCP)
Author-email: Aliyun MCP Developer <developer@example.com>
License: MIT License
Project-URL: Homepage, https://github.com/example/aliyun-mcp-weather-skill
Project-URL: Repository, https://github.com/example/aliyun-mcp-weather-skill
Classifier: Programming Language :: Python :: 3
Classifier: License :: OSI Approved :: MIT License
Classifier: Operating System :: OS Independent
Classifier: Topic :: Software Development :: Libraries :: Python Modules
Classifier: Intended Audience :: Developers
Requires-Python: >=3.8
License-File: LICENSE
Dynamic: license-file
